{
"type": "FeatureCollection",
"features": [
{ "type": "Feature", "properties": { "Name": "Swan's Island LTREB", "tessellate": -1, "extrude": 0, "visibility": -1 }, "geometry": { "type": "Point", "coordinates": [ -68.4514095, 44.1454423, 0.0 ] } },
{ "type": "Feature", "properties": { "Name": "West Falmouth Harbor LTREB", "tessellate": -1, "extrude": 0, "visibility": -1 }, "geometry": { "type": "Point", "coordinates": [ -70.6494753, 41.6056631, 0.0 ] } },
{ "type": "Feature", "properties": { "Name": "North Inlet LTREB", "tessellate": -1, "extrude": 0, "visibility": -1 }, "geometry": { "type": "Point", "coordinates": [ -79.165617, 33.3293508, 0.0 ] } },
{ "type": "Feature", "properties": { "Name": "SERC GCREW LTREB", "tessellate": -1, "extrude": 0, "visibility": -1 }, "geometry": { "type": "Point", "coordinates": [ -76.5466181, 38.8853928, 0.0 ] } }
]
}
